orix/__init__.py
orix/_base.py
orix/_util.py
orix/constants.py
orix/crystal_map/__init__.py
orix/crystal_map/crystal_map.py
orix/crystal_map/crystal_map_properties.py
orix/crystal_map/phase_list.py
orix/data/__init__.py
orix/data/_registry.py
orix/io/__init__.py
orix/io/plugins/__init__.py
orix/io/plugins/_h5ebsd.py
orix/io/plugins/ang.py
orix/io/plugins/bruker_h5ebsd.py
orix/io/plugins/ctf.py
orix/io/plugins/emsoft_h5ebsd.py
orix/io/plugins/orix_hdf5.py
orix/measure/__init__.py
orix/measure/pole_density_function.py
orix/plot/__init__.py
orix/plot/_symmetry_marker.py
orix/plot/_util.py
orix/plot/crystal_map_plot.py
orix/plot/inverse_pole_figure_plot.py
orix/plot/rotation_plot.py
orix/plot/stereographic_plot.py
orix/plot/unit_cell_plot.py
orix/plot/direction_color_keys/__init__.py
orix/plot/direction_color_keys/_util.py
orix/plot/direction_color_keys/direction_color_key.py
orix/plot/direction_color_keys/direction_color_key_tsl.py
orix/plot/orientation_color_keys/__init__.py
orix/plot/orientation_color_keys/euler_color_key.py
orix/plot/orientation_color_keys/ipf_color_key.py
orix/plot/orientation_color_keys/ipf_color_key_tsl.py
orix/projections/__init__.py
orix/projections/stereographic.py
orix/quaternion/__init__.py
orix/quaternion/_conversions.py
orix/quaternion/misorientation.py
orix/quaternion/orientation.py
orix/quaternion/orientation_region.py
orix/quaternion/quaternion.py
orix/quaternion/rotation.py
orix/quaternion/symmetry.py
orix/sampling/S2_sampling.py
orix/sampling/SO3_sampling.py
orix/sampling/__init__.py
orix/sampling/_cubochoric_sampling.py
orix/sampling/_polyhedral_sampling.py
orix/sampling/sample_generators.py
orix/tests/__init__.py
orix/tests/conftest.py
orix/tests/test_axangle.py
orix/tests/test_constants.py
orix/tests/test_crystal_map.py
orix/tests/test_crystal_map_properties.py
orix/tests/test_fundamental_sector.py
orix/tests/test_measure.py
orix/tests/test_miller.py
orix/tests/test_neoeuler.py
orix/tests/test_object3d.py
orix-0.13.3.dist-info/METADATA
orix-0.13.3.dist-info/WHEEL
orix-0.13.3.dist-info/licenses/LICENSE
orix-0.13.3.dist-info/RECORD
