Metadata-Version: 2.4
Name: orix
Version: 0.13.3
Summary: orix is an open-source Python library for handling crystal orientation mapping data
Author: orix developers
License: GNU GENERAL PUBLIC LICENSE
License-File: LICENSE
Classifier: Development Status :: 4 - Beta
Classifier: Intended Audience :: Science/Research
Classifier: License :: OSI Approved :: GNU General Public License v3 or later (GPLv3+)
Classifier: Natural Language :: English
Classifier: Operating System :: OS Independent
Classifier: Programming Language :: Python :: 3
Classifier: Programming Language :: Python :: 3.10
Classifier: Programming Language :: Python :: 3.11
Classifier: Programming Language :: Python :: 3.12
Classifier: Topic :: Scientific/Engineering
Classifier: Topic :: Scientific/Engineering :: Physics
Requires-Python: >=3.10
Requires-Dist: dask[array]
Requires-Dist: diffpy-structure>=3.0.2
Requires-Dist: h5py
Requires-Dist: matplotlib-scalebar
Requires-Dist: matplotlib>=3.6.1
Requires-Dist: numba
Requires-Dist: numpy
Requires-Dist: pooch>=0.13
Requires-Dist: pycifrw
Requires-Dist: scipy
Requires-Dist: tqdm
Requires-Dist: typing-extensions
Provides-Extra: all
Requires-Dist: numpy-quaternion; extra == 'all'
Provides-Extra: coverage
Requires-Dist: coverage>=5.0; extra == 'coverage'
Requires-Dist: pytest-cov>=2.8.1; extra == 'coverage'
Provides-Extra: dev
Requires-Dist: black[jupyter]; extra == 'dev'
Requires-Dist: coverage>=5.0; extra == 'dev'
Requires-Dist: hatch; extra == 'dev'
Requires-Dist: ipykernel; extra == 'dev'
Requires-Dist: isort>=5.10; extra == 'dev'
Requires-Dist: licenseheaders; extra == 'dev'
Requires-Dist: memory-profiler; extra == 'dev'
Requires-Dist: nbconvert>=7.16.4; extra == 'dev'
Requires-Dist: nbsphinx>=0.7; extra == 'dev'
Requires-Dist: numpydoc; extra == 'dev'
Requires-Dist: outdated; extra == 'dev'
Requires-Dist: pre-commit>=1.16; extra == 'dev'
Requires-Dist: pydata-sphinx-theme; extra == 'dev'
Requires-Dist: pytest-cov>=2.8.1; extra == 'dev'
Requires-Dist: pytest-rerunfailures; extra == 'dev'
Requires-Dist: pytest-xdist; extra == 'dev'
Requires-Dist: pytest>=5.4; extra == 'dev'
Requires-Dist: scikit-image; extra == 'dev'
Requires-Dist: scikit-learn; extra == 'dev'
Requires-Dist: sphinx-codeautolink[ipython]; extra == 'dev'
Requires-Dist: sphinx-copybutton>=0.2.5; extra == 'dev'
Requires-Dist: sphinx-design; extra == 'dev'
Requires-Dist: sphinx-gallery; extra == 'dev'
Requires-Dist: sphinx>=3.0.2; extra == 'dev'
Requires-Dist: sphinxcontrib-bibtex>=1.0; extra == 'dev'
Provides-Extra: doc
Requires-Dist: ipykernel; extra == 'doc'
Requires-Dist: memory-profiler; extra == 'doc'
Requires-Dist: nbconvert>=7.16.4; extra == 'doc'
Requires-Dist: nbsphinx>=0.7; extra == 'doc'
Requires-Dist: numpydoc; extra == 'doc'
Requires-Dist: pydata-sphinx-theme; extra == 'doc'
Requires-Dist: scikit-image; extra == 'doc'
Requires-Dist: scikit-learn; extra == 'doc'
Requires-Dist: sphinx-codeautolink[ipython]; extra == 'doc'
Requires-Dist: sphinx-copybutton>=0.2.5; extra == 'doc'
Requires-Dist: sphinx-design; extra == 'doc'
Requires-Dist: sphinx-gallery; extra == 'doc'
Requires-Dist: sphinx>=3.0.2; extra == 'doc'
Requires-Dist: sphinxcontrib-bibtex>=1.0; extra == 'doc'
Provides-Extra: tests
Requires-Dist: numpydoc; extra == 'tests'
Requires-Dist: pytest-rerunfailures; extra == 'tests'
Requires-Dist: pytest-xdist; extra == 'tests'
Requires-Dist: pytest>=5.4; extra == 'tests'
